Workbook

Sheet 月次PL
A1: 月次P/L（12ヶ月）: 結婚式タイムカプセルワイン事業
A2: ※青文字: ユーザー入力値、黒文字: 数式計算値
A4: 項目 | B4: 種別 | C4: M1 | D4: M2 | E4: M3 | F4: M4 | G4: M5 | H4: M6 | I4: M7 | J4: M8 | K4: M9 | L4: M10 | M4: M11 | N4: M12 | O4: Year 1計
A5: 販売本数 | B5: 入力 | C5: 0 | D5: 0 | E5: 5 | F5: 10 | G5: 5 | H5: 8 | I5: 8 | J5: 10 | K5: 10 | L5: 10 | M5: 10 | N5: 9 | O5: =SUM(C5:N5)
A6: 平均単価（円） | B6: 入力 | C6: 12000 | D6: 12000 | E6: 10800 | F6: 10800 | G6: 12000 | H6: 12000 | I6: 12000 | J6: 12000 | K6: 12000 | L6: 12000 | M6: 12000 | N6: 12000 | O6: =SUM(C6:N6)
A7: 売上 | B7: 計算 | C7: =C5*C6 | D7: =D5*D6 | E7: =E5*E6 | F7: =F5*F6 | G7: =G5*G6 | H7: =H5*H6 | I7: =I5*I6 | J7: =J5*J6 | ... N7: =N5*N6 | O7: =SUM(C7:N7)
A8: 原価（ワイン・資材・送料） | B8: 計算 | C8: =C5*5000 | D8: =D5*5000 | E8: =E5*5000 | F8: =F5*5000 | G8: =G5*5000 | H8: =H5*5000 | I8: =I5*5000 | J8: =J5*5000 | ... N8: =N5*5000 | O8: =SUM(C8:N8)
A9: 決済/CF手数料 | B9: 計算 | C9: =C7*0.04 | D9: =D7*0.04 | E9: =E7*0.20 | F9: =F7*0.20 | G9: =G7*0.04 | H9: =H7*0.04 | I9: =I7*0.04 | J9: =J7*0.04 | K9: =K7*0.04 | L9: =L7*0.04 | M9: =M7*0.04 | N9: =N7*0.04 | O9: =SUM(C9:N9)
A10: 粗利 | B10: 計算 | C10: =C7-C8-C9 | D10: =D7-D8-D9 | E10: =E7-E8-E9 | F10: =F7-F8-F9 | G10: =G7-G8-G9 | H10: =H7-H8-H9 | I10: =I7-I8-I9 | J10: =J7-J8-J9 | ... N10: =N7-N8-N9 | O10: =SUM(C10:N10)
A11: 粗利率 | B11: 計算 | C11: =IF(C7=0,"",C10/C7) | D11: =IF(D7=0,"",D10/D7) | E11: =IF(E7=0,"",E10/E7) | F11: =IF(F7=0,"",F10/F7) | G11: =IF(G7=0,"",G10/G7) | H11: =IF(H7=0,"",H10/H7) | I11: =IF(I7=0,"",I10/I7) | J11: =IF(J7=0,"",J10/J7) | ... N11: =IF(N7=0,"",N10/N7)
A12: 固定費（EC/SaaS/通信） | B12: 入力 | C12: 0 | D12: 0 | E12: 0 | F12: 0 | G12: 15000 | H12: 15000 | I12: 15000 | J12: 15000 | K12: 15000 | L12: 15000 | M12: 15000 | N12: 15000 | O12: =SUM(C12:N12)
A13: 広告費 | B13: 入力 | C13: 5000 | D13: 5000 | E13: 20000 | F13: 15000 | G13: 20000 | H13: 25000 | I13: 25000 | J13: 25000 | K13: 25000 | L13: 25000 | M13: 25000 | N13: 25000 | O13: =SUM(C13:N13)
A14: その他販管費 | B14: 入力 | C14: 10000 | D14: 10000 | E14: 10000 | F14: 10000 | G14: 5000 | H14: 5000 | I14: 5000 | J14: 5000 | K14: 5000 | L14: 5000 | M14: 5000 | N14: 5000 | O14: =SUM(C14:N14)
A15: 営業利益 | B15: 計算 | C15: =C10-C12-C13-C14 | D15: =D10-D12-D13-D14 | E15: =E10-E12-E13-E14 | F15: =F10-F12-F13-F14 | G15: =G10-G12-G13-G14 | H15: =H10-H12-H13-H14 | I15: =I10-I12-I13-I14 | J15: =J10-J12-J13-J14 | ... N15: =N10-N12-N13-N14 | O15: =SUM(C15:N15)
A16: 営業利益率 | B16: 計算 | C16: =IF(C7=0,"",C15/C7) | D16: =IF(D7=0,"",D15/D7) | E16: =IF(E7=0,"",E15/E7) | F16: =IF(F7=0,"",F15/F7) | G16: =IF(G7=0,"",G15/G7) | H16: =IF(H7=0,"",H15/H7) | I16: =IF(I7=0,"",I15/I7) | J16: =IF(J7=0,"",J15/J7) | ... N16: =IF(N7=0,"",N15/N7)
A17: 累計営業利益 | B17: 計算 | C17: =C15 | D17: =C17+D15 | E17: =D17+E15 | F17: =E17+F15 | G17: =F17+G15 | H17: =G17+H15 | I17: =H17+I15 | J17: =I17+J15 | K17: =J17+K15 | ... N17: =M17+N15 | O17: =SUM(C17:N17)

Sheet キャッシュフロー
A1: キャッシュフロー計算書（12ヶ月）
A3: 項目 | B3: 種別 | C3: M1 | D3: M2 | E3: M3 | F3: M4 | G3: M5 | H3: M6 | I3: M7 | J3: M8 | K3: M9 | L3: M10 | M3: M11 | N3: M12 | O3: Year 1計
A4: 期首現金残高 | B4: 計算 | C4: 200000 | D4: =C6 | E4: =D6 | F4: =E6 | G4: =F6 | H4: =G6 | I4: =H6 | J4: =I6 | K4: =J6 | ... N4: =M6 | O4: =N4
A5: 営業CF（営業利益） | B5: 参照 | C5: ='月次PL'!C15 | D5: ='月次PL'!D15 | E5: ='月次PL'!E15 | F5: ='月次PL'!F15 | G5: ='月次PL'!G15 | H5: ='月次PL'!H15 | I5: ='月次PL'!I15 | J5: ='月次PL'!J15 | ... N5: ='月次PL'!N15 | O5: =SUM(C5:N5)
A6: 期末現金残高 | B6: 計算 | C6: =C4+C5 | D6: =D4+D5 | E6: =E4+E5 | F6: =F4+F5 | G6: =G4+G5 | H6: =H4+H5 | I6: =I4+I5 | J6: =J4+J5 | ... N6: =N4+N5 | O6: =N6

Sheet ユニットエコノミクス
A1: ユニットエコノミクス追跡
A3: 指標 | B3: 計算式 | C3: 目標値 | D3: 実績値 | E3: 評価
A4: 販売単価 | B4: 売上 / 販売本数 | C4: 12,000円
A5: 原価/本 | B5: ワイン+ラベル+箱+送料+手数料 | C5: 5,000円
A6: 粗利/本 | B6: 販売単価 - 原価 | C6: 7,000円
A7: 粗利率 | B7: 粗利 / 売上 | C7: 58%
A8: CAC | B8: 広告費 / 新規顧客数 | C8: 2,500円
A9: ARPU | B9: 平均顧客単価 | C9: 15,000円
A10: リピート率 | B10: 2回以上購入 / 全顧客 | C10: 15%
A11: LTV | B11: ARPU × (1 + リピート率) | C11: 18,750円
A12: LTV/CAC | B12: LTV / CAC | C12: 7.5倍
A13: 粗利/CAC | B13: 粗利 / CAC | C13: 2.8倍
A14: 回収期間 | B14: - | C14: 即時（先払い）

Sheet 予算管理
A1: 予算管理: フェーズ別予算 vs 実績
A3: フェーズ | B3: カテゴリ | C3: 予算 | D3: 実績 | E3: 差異 | F3: 消化率
A4: Phase A（M1-2） | B4: 免許申請費用 | C4: 30000 | E4: =C4-D4 | F4: =IF(C4=0,"",D4/C4)
A5: Phase A（M1-2） | B5: サンプル制作費 | C5: 40000 | E5: =C5-D5 | F5: =IF(C5=0,"",D5/C5)
A6: Phase A（M1-2） | B6: 撮影・素材制作 | C6: 20000 | E6: =C6-D6 | F6: =IF(C6=0,"",D6/C6)
A7: Phase A（M1-2） | B7: 予備費 | C7: 10000 | E7: =C7-D7 | F7: =IF(C7=0,"",D7/C7)
A8: Phase A 小計 | C8: =SUM(C4:C7) | D8: =SUM(D4:D7) | E8: =C8-D8 | F8: =IF(C8=0,"",D8/C8)
A9: Phase B（M3-4） | B9: 広告・PR費 | C9: 30000 | E9: =C9-D9 | F9: =IF(C9=0,"",D9/C9)
A10: Phase B（M3-4） | B10: 追加サンプル制作 | C10: 20000 | E10: =C10-D10 | F10: =IF(C10=0,"",D10/C10)
A11: Phase B（M3-4） | B11: 予備費 | C11: 20000 | E11: =C11-D11 | F11: =IF(C11=0,"",D11/C11)
A12: Phase B 小計 | C12: =SUM(C9:C11) | D12: =SUM(D9:D11) | E12: =C12-D12 | F12: =IF(C12=0,"",D12/C12)
A13: Phase C（M5-12） | B13: EC基盤月額 | C13: 32000 | E13: =C13-D13 | F13: =IF(C13=0,"",D13/C13)
A14: Phase C（M5-12） | B14: 広告費 | C14: 200000 | E14: =C14-D14 | F14: =IF(C14=0,"",D14/C14)
A15: Phase C（M5-12） | B15: AIツール | C15: 24000 | E15: =C15-D15 | F15: =IF(C15=0,"",D15/C15)
A16: Phase C（M5-12） | B16: その他 | C16: 40000 | E16: =C16-D16 | F16: =IF(C16=0,"",D16/C16)
A17: Phase C 小計 | C17: =SUM(C13:C16) | D17: =SUM(D13:D16) | E17: =C17-D17 | F17: =IF(C17=0,"",D17/C17)
A18: Year 1 合計 | C18: =C8+C12+C17 | D18: =D8+D12+D17 | E18: =C18-D18 | F18: =IF(C18=0,"",D18/C18)
